dynex/__init__.py
dynex/dynex_circuit.py
dynex-0.1.26.dist-info/LICENSE
dynex-0.1.26.dist-info/METADATA
dynex-0.1.26.dist-info/WHEEL
dynex-0.1.26.dist-info/top_level.txt
dynex-0.1.26.dist-info/RECORD
